RainbowPrint/RainbowPrint.py
RainbowPrint/__init__.py
RainbowPrint-2.0.0.dist-info/METADATA
RainbowPrint-2.0.0.dist-info/RECORD
RainbowPrint-2.0.0.dist-info/WHEEL
RainbowPrint-2.0.0.dist-info/top_level.txt
