Metadata-Version: 2.1
Name: RainbowPrint
Version: 2.0.0
Summary: 在终端中输出彩色文本
Home-page: UNKNOWN
Author: hs
Author-email: huangshengtx@163.com
License: UNKNOWN
Platform: UNKNOWN
